[1,["5ftTMDeTlFO6+aalNkLrhn@6c48a"],["_textureSource"],["cc.SpriteFrame"],0,[{"name":"pic_battle_huan5_0070","rect":{"x":0,"y":17,"width":209,"height":207},"offset":{"x":-5.5,"y":-8.5},"originalSize":{"width":220,"height":224},"rotated":false,"capInsets":[0,0,0,0],"vertices":{"rawPosition":[-104.5,-103.5,0,104.5,-103.5,0,-104.5,103.5,0,104.5,103.5,0],"indexes":[0,1,2,2,1,3],"uv":[0,207,209,207,0,0,209,0],"nuv":[0,0,0.95,0,0,0.9241071428571429,0.95,0.9241071428571429],"minPos":{"x":-104.5,"y":-103.5,"z":0},"maxPos":{"x":104.5,"y":103.5,"z":0}},"packable":true,"pixelsToUnit":100,"pivot":{"x":0.5,"y":0.5},"meshType":0}],[0],0,[0],[0],[0]]
