[1,["9bdhkswxNFlqUYHQZzNGGo@6c48a"],["_textureSource"],["cc.SpriteFrame","cc.SpriteAtlas"],0,[[[{"name":"pic_hangup","spriteFrames":["aim_hangup_00","daTVbzYR5OuqP06HBmi0B9@036ed","aim_hangup_01","daTVbzYR5OuqP06HBmi0B9@edd0f","aim_hangup_02","daTVbzYR5OuqP06HBmi0B9@8c88c","aim_hangup_03","daTVbzYR5OuqP06HBmi0B9@f8b76","box_hangup_chapter_00","daTVbzYR5OuqP06HBmi0B9@f6f80","box_hangup_chapter_01","daTVbzYR5OuqP06HBmi0B9@993a3","box_hangup_chapter_02","daTVbzYR5OuqP06HBmi0B9@74832","btn_hangup_check_00","daTVbzYR5OuqP06HBmi0B9@0d1ab","btn_hangup_check_01","daTVbzYR5OuqP06HBmi0B9@47dee","btn_hangup_check_02","daTVbzYR5OuqP06HBmi0B9@5aa20","btn_hangup_check_03","daTVbzYR5OuqP06HBmi0B9@5e2db","btn_hangup_check_quick","daTVbzYR5OuqP06HBmi0B9@0e47e","btn_hangup_go","daTVbzYR5OuqP06HBmi0B9@68ac3","btn_hangup_pokedex","daTVbzYR5OuqP06HBmi0B9@27ffd","exp_hangup_00","daTVbzYR5OuqP06HBmi0B9@1d768","exp_hangup_01","daTVbzYR5OuqP06HBmi0B9@fff47","pic_hangup_buff_01","daTVbzYR5OuqP06HBmi0B9@0ca9a","pic_hangup_buff_02","daTVbzYR5OuqP06HBmi0B9@c6ca0","pic_hangup_exp_bg","daTVbzYR5OuqP06HBmi0B9@7809e","pic_hangup_go_female","daTVbzYR5OuqP06HBmi0B9@8b94d","pic_hangup_go_jng","daTVbzYR5OuqP06HBmi0B9@1c561","pic_hangup_go_jng_1","daTVbzYR5OuqP06HBmi0B9@ab0b1","pic_hangup_go_jng_2","daTVbzYR5OuqP06HBmi0B9@843a5","pic_hangup_go_male","daTVbzYR5OuqP06HBmi0B9@355f5","pic_hangup_go_mwzz","daTVbzYR5OuqP06HBmi0B9@23e50","pic_hangup_go_mwzz_1","daTVbzYR5OuqP06HBmi0B9@5119d","pic_hangup_go_mwzz_2","daTVbzYR5OuqP06HBmi0B9@1eb47","pic_hangup_go_pkq","daTVbzYR5OuqP06HBmi0B9@17777","pic_hangup_go_pkq_1","daTVbzYR5OuqP06HBmi0B9@6cf94","pic_hangup_go_pkq_2","daTVbzYR5OuqP06HBmi0B9@78de6","pic_hangup_go_xhl","daTVbzYR5OuqP06HBmi0B9@af9f9","pic_hangup_go_xhl_1","daTVbzYR5OuqP06HBmi0B9@09c0b","pic_hangup_go_xhl_2","daTVbzYR5OuqP06HBmi0B9@a07bf","pic_hangup_pokedex_exp_01","daTVbzYR5OuqP06HBmi0B9@24adc","pic_hangup_pokedex_exp_02","daTVbzYR5OuqP06HBmi0B9@0a309","pic_hangup_search_coin","daTVbzYR5OuqP06HBmi0B9@86bb9","pic_hangup_search_coin_1","daTVbzYR5OuqP06HBmi0B9@bf5c2","pic_hangup_search_diamond","daTVbzYR5OuqP06HBmi0B9@11dcb","pic_hangup_search_exp","daTVbzYR5OuqP06HBmi0B9@bf15d","pic_hangup_search_exp_1","daTVbzYR5OuqP06HBmi0B9@c072e","pic_hangup_search_stone","daTVbzYR5OuqP06HBmi0B9@2f13b","pic_hangup_search_stone_1","daTVbzYR5OuqP06HBmi0B9@c0c8d","pic_hangup_search_stone_2","daTVbzYR5OuqP06HBmi0B9@9046c","pic_hangup_search_wood","daTVbzYR5OuqP06HBmi0B9@53637","pic_hangup_target_1","daTVbzYR5OuqP06HBmi0B9@24a76","pic_hangup_target_1_1","daTVbzYR5OuqP06HBmi0B9@e73e1","pic_hangup_target_2","daTVbzYR5OuqP06HBmi0B9@07433","pic_hangup_target_3","daTVbzYR5OuqP06HBmi0B9@f7e77","pic_hangup_target_4","daTVbzYR5OuqP06HBmi0B9@13f28","pic_hangup_target_5","daTVbzYR5OuqP06HBmi0B9@88dc9","pic_hangup_target_6","daTVbzYR5OuqP06HBmi0B9@a0bdf","pic_hangup_target_7","daTVbzYR5OuqP06HBmi0B9@7934f","pic_maintask_doing_0","daTVbzYR5OuqP06HBmi0B9@663c7","pic_maintask_doing_1","daTVbzYR5OuqP06HBmi0B9@ed94b","pic_maintask_done_0","daTVbzYR5OuqP06HBmi0B9@b8b2f","pic_maintask_done_1","daTVbzYR5OuqP06HBmi0B9@ef90a"]}],[1],0,[],[],[]],[[{"name":"aim_hangup_00","rect":{"x":809,"y":784,"width":85,"height":44},"offset":{"x":0,"y":0},"originalSize":{"width":87,"height":44},"rotated":false,"capInsets":[0,0,0,0],"vertices":{"rawPosition":[],"indexes":[],"uv":[],"nuv":[],"minPos":{"x":0,"y":0,"z":0},"maxPos":{"x":0,"y":0,"z":0}},"packable":true,"pixelsToUnit":100,"pivot":{"x":0.5,"y":0.5},"meshType":0}],[0],0,[0],[0],[0]],[[{"name":"pic_hangup_target_2","rect":{"x":816,"y":458,"width":134,"height":150},"offset":{"x":0,"y":0},"originalSize":{"width":134,"height":150},"rotated":false,"capInsets":[0,0,0,0],"vertices":{"rawPosition":[],"indexes":[],"uv":[],"nuv":[],"minPos":{"x":0,"y":0,"z":0},"maxPos":{"x":0,"y":0,"z":0}},"packable":true,"pixelsToUnit":100,"pivot":{"x":0.5,"y":0.5},"meshType":0}],[0],0,[0],[0],[0]],[[{"name":"pic_hangup_go_xhl_1","rect":{"x":847,"y":912,"width":48,"height":47},"offset":{"x":0,"y":0},"originalSize":{"width":48,"height":47},"rotated":false,"capInsets":[0,0,0,0],"vertices":{"rawPosition":[],"indexes":[],"uv":[],"nuv":[],"minPos":{"x":0,"y":0,"z":0},"maxPos":{"x":0,"y":0,"z":0}},"packable":true,"pixelsToUnit":100,"pivot":{"x":0.5,"y":0.5},"meshType":0}],[0],0,[0],[0],[0]],[[{"name":"pic_hangup_pokedex_exp_02","rect":{"x":904,"y":672,"width":58,"height":58},"offset":{"x":0,"y":0},"originalSize":{"width":60,"height":60},"rotated":false,"capInsets":[0,0,0,0],"vertices":{"rawPosition":[],"indexes":[],"uv":[],"nuv":[],"minPos":{"x":0,"y":0,"z":0},"maxPos":{"x":0,"y":0,"z":0}},"packable":true,"pixelsToUnit":100,"pivot":{"x":0.5,"y":0.5},"meshType":0}],[0],0,[0],[0],[0]],[[{"name":"pic_hangup_buff_01","rect":{"x":762,"y":768,"width":45,"height":45},"offset":{"x":0,"y":0},"originalSize":{"width":45,"height":45},"rotated":false,"capInsets":[0,0,0,0],"vertices":{"rawPosition":[],"indexes":[],"uv":[],"nuv":[],"minPos":{"x":0,"y":0,"z":0},"maxPos":{"x":0,"y":0,"z":0}},"packable":true,"pixelsToUnit":100,"pivot":{"x":0.5,"y":0.5},"meshType":0}],[0],0,[0],[0],[0]],[[{"name":"btn_hangup_check_00","rect":{"x":2,"y":952,"width":188,"height":68},"offset":{"x":0,"y":1},"originalSize":{"width":188,"height":70},"rotated":false,"capInsets":[0,0,0,0],"vertices":{"rawPosition":[],"indexes":[],"uv":[],"nuv":[],"minPos":{"x":0,"y":0,"z":0},"maxPos":{"x":0,"y":0,"z":0}},"packable":true,"pixelsToUnit":100,"pivot":{"x":0.5,"y":0.5},"meshType":0}],[0],0,[0],[0],[0]],[[{"name":"btn_hangup_check_quick","rect":{"x":737,"y":688,"width":70,"height":78},"offset":{"x":-2,"y":0},"originalSize":{"width":76,"height":82},"rotated":false,"capInsets":[0,0,0,0],"vertices":{"rawPosition":[],"indexes":[],"uv":[],"nuv":[],"minPos":{"x":0,"y":0,"z":0},"maxPos":{"x":0,"y":0,"z":0}},"packable":true,"pixelsToUnit":100,"pivot":{"x":0.5,"y":0.5},"meshType":0}],[0],0,[0],[0],[0]],[[{"name":"pic_hangup_search_diamond","rect":{"x":2,"y":2,"width":461,"height":318},"offset":{"x":-4,"y":1},"originalSize":{"width":475,"height":324},"rotated":false,"capInsets":[0,0,0,0],"vertices":{"rawPosition":[],"indexes":[],"uv":[],"nuv":[],"minPos":{"x":0,"y":0,"z":0},"maxPos":{"x":0,"y":0,"z":0}},"packable":true,"pixelsToUnit":100,"pivot":{"x":0.5,"y":0.5},"meshType":0}],[0],0,[0],[0],[0]],[[{"name":"pic_hangup_target_4","rect":{"x":680,"y":452,"width":134,"height":150},"offset":{"x":0,"y":0},"originalSize":{"width":134,"height":150},"rotated":false,"capInsets":[0,0,0,0],"vertices":{"rawPosition":[],"indexes":[],"uv":[],"nuv":[],"minPos":{"x":0,"y":0,"z":0},"maxPos":{"x":0,"y":0,"z":0}},"packable":true,"pixelsToUnit":100,"pivot":{"x":0.5,"y":0.5},"meshType":0}],[0],0,[0],[0],[0]],[[{"name":"pic_hangup_go_pkq","rect":{"x":830,"y":886,"width":34,"height":24},"offset":{"x":0,"y":0},"originalSize":{"width":34,"height":24},"rotated":false,"capInsets":[0,0,0,0],"vertices":{"rawPosition":[],"indexes":[],"uv":[],"nuv":[],"minPos":{"x":0,"y":0,"z":0},"maxPos":{"x":0,"y":0,"z":0}},"packable":true,"pixelsToUnit":100,"pivot":{"x":0.5,"y":0.5},"meshType":0}],[0],0,[0],[0],[0]],[[{"name":"pic_hangup_go_jng","rect":{"x":762,"y":815,"width":36,"height":32},"offset":{"x":0,"y":0},"originalSize":{"width":36,"height":32},"rotated":false,"capInsets":[0,0,0,0],"vertices":{"rawPosition":[],"indexes":[],"uv":[],"nuv":[],"minPos":{"x":0,"y":0,"z":0},"maxPos":{"x":0,"y":0,"z":0}},"packable":true,"pixelsToUnit":100,"pivot":{"x":0.5,"y":0.5},"meshType":0}],[0],0,[0],[0],[0]],[[{"name":"exp_hangup_00","rect":{"x":192,"y":952,"width":358,"height":26},"offset":{"x":0,"y":0},"originalSize":{"width":358,"height":26},"rotated":false,"capInsets":[0,0,0,0],"vertices":{"rawPosition":[],"indexes":[],"uv":[],"nuv":[],"minPos":{"x":0,"y":0,"z":0},"maxPos":{"x":0,"y":0,"z":0}},"packable":true,"pixelsToUnit":100,"pivot":{"x":0.5,"y":0.5},"meshType":0}],[0],0,[0],[0],[0]],[[{"name":"pic_hangup_go_mwzz_2","rect":{"x":847,"y":961,"width":48,"height":44},"offset":{"x":0,"y":0},"originalSize":{"width":48,"height":44},"rotated":false,"capInsets":[0,0,0,0],"vertices":{"rawPosition":[],"indexes":[],"uv":[],"nuv":[],"minPos":{"x":0,"y":0,"z":0},"maxPos":{"x":0,"y":0,"z":0}},"packable":true,"pixelsToUnit":100,"pivot":{"x":0.5,"y":0.5},"meshType":0}],[0],0,[0],[0],[0]],[[{"name":"pic_hangup_go_mwzz","rect":{"x":347,"y":581,"width":32,"height":30},"offset":{"x":0,"y":0},"originalSize":{"width":32,"height":30},"rotated":false,"capInsets":[0,0,0,0],"vertices":{"rawPosition":[],"indexes":[],"uv":[],"nuv":[],"minPos":{"x":0,"y":0,"z":0},"maxPos":{"x":0,"y":0,"z":0}},"packable":true,"pixelsToUnit":100,"pivot":{"x":0.5,"y":0.5},"meshType":0}],[0],0,[0],[0],[0]],[[{"name":"pic_hangup_target_1","rect":{"x":601,"y":617,"width":134,"height":150},"offset":{"x":0,"y":0},"originalSize":{"width":134,"height":150},"rotated":false,"capInsets":[0,0,0,0],"vertices":{"rawPosition":[],"indexes":[],"uv":[],"nuv":[],"minPos":{"x":0,"y":0,"z":0},"maxPos":{"x":0,"y":0,"z":0}},"packable":true,"pixelsToUnit":100,"pivot":{"x":0.5,"y":0.5},"meshType":0}],[0],0,[0],[0],[0]],[[{"name":"pic_hangup_pokedex_exp_01","rect":{"x":791,"y":913,"width":54,"height":54},"offset":{"x":0,"y":0},"originalSize":{"width":54,"height":54},"rotated":false,"capInsets":[0,0,0,0],"vertices":{"rawPosition":[],"indexes":[],"uv":[],"nuv":[],"minPos":{"x":0,"y":0,"z":0},"maxPos":{"x":0,"y":0,"z":0}},"packable":true,"pixelsToUnit":100,"pivot":{"x":0.5,"y":0.5},"meshType":0}],[0],0,[0],[0],[0]],[[{"name":"btn_hangup_pokedex","rect":{"x":694,"y":769,"width":66,"height":78},"offset":{"x":0,"y":-1},"originalSize":{"width":76,"height":82},"rotated":false,"capInsets":[0,0,0,0],"vertices":{"rawPosition":[],"indexes":[],"uv":[],"nuv":[],"minPos":{"x":0,"y":0,"z":0},"maxPos":{"x":0,"y":0,"z":0}},"packable":true,"pixelsToUnit":100,"pivot":{"x":0.5,"y":0.5},"meshType":0}],[0],0,[0],[0],[0]],[[{"name":"pic_hangup_search_stone","rect":{"x":465,"y":2,"width":364,"height":276},"offset":{"x":0,"y":2},"originalSize":{"width":366,"height":280},"rotated":false,"capInsets":[0,0,0,0],"vertices":{"rawPosition":[],"indexes":[],"uv":[],"nuv":[],"minPos":{"x":0,"y":0,"z":0},"maxPos":{"x":0,"y":0,"z":0}},"packable":true,"pixelsToUnit":100,"pivot":{"x":0.5,"y":0.5},"meshType":0}],[0],0,[0],[0],[0]],[[{"name":"pic_hangup_go_male","rect":{"x":788,"y":849,"width":40,"height":62},"offset":{"x":0,"y":0},"originalSize":{"width":40,"height":62},"rotated":false,"capInsets":[0,0,0,0],"vertices":{"rawPosition":[],"indexes":[],"uv":[],"nuv":[],"minPos":{"x":0,"y":0,"z":0},"maxPos":{"x":0,"y":0,"z":0}},"packable":true,"pixelsToUnit":100,"pivot":{"x":0.5,"y":0.5},"meshType":0}],[0],0,[0],[0],[0]],[[{"name":"btn_hangup_check_01","rect":{"x":347,"y":850,"width":22,"height":10},"offset":{"x":0,"y":0},"originalSize":{"width":22,"height":10},"rotated":false,"capInsets":[0,0,0,0],"vertices":{"rawPosition":[],"indexes":[],"uv":[],"nuv":[],"minPos":{"x":0,"y":0,"z":0},"maxPos":{"x":0,"y":0,"z":0}},"packable":true,"pixelsToUnit":100,"pivot":{"x":0.5,"y":0.5},"meshType":0}],[0],0,[0],[0],[0]],[[{"name":"pic_hangup_go_mwzz_1","rect":{"x":897,"y":943,"width":42,"height":39},"offset":{"x":0,"y":0},"originalSize":{"width":42,"height":39},"rotated":false,"capInsets":[0,0,0,0],"vertices":{"rawPosition":[],"indexes":[],"uv":[],"nuv":[],"minPos":{"x":0,"y":0,"z":0},"maxPos":{"x":0,"y":0,"z":0}},"packable":true,"pixelsToUnit":100,"pivot":{"x":0.5,"y":0.5},"meshType":0}],[0],0,[0],[0],[0]],[[{"name":"pic_hangup_search_wood","rect":{"x":2,"y":322,"width":406,"height":257},"offset":{"x":1,"y":2},"originalSize":{"width":410,"height":263},"rotated":false,"capInsets":[0,0,0,0],"vertices":{"rawPosition":[],"indexes":[],"uv":[],"nuv":[],"minPos":{"x":0,"y":0,"z":0},"maxPos":{"x":0,"y":0,"z":0}},"packable":true,"pixelsToUnit":100,"pivot":{"x":0.5,"y":0.5},"meshType":0}],[0],0,[0],[0],[0]],[[{"name":"btn_hangup_check_02","rect":{"x":680,"y":604,"width":20,"height":10},"offset":{"x":0,"y":0},"originalSize":{"width":20,"height":10},"rotated":false,"capInsets":[0,0,0,0],"vertices":{"rawPosition":[],"indexes":[],"uv":[],"nuv":[],"minPos":{"x":0,"y":0,"z":0},"maxPos":{"x":0,"y":0,"z":0}},"packable":true,"pixelsToUnit":100,"pivot":{"x":0.5,"y":0.5},"meshType":0}],[0],0,[0],[0],[0]],[[{"name":"btn_hangup_check_03","rect":{"x":866,"y":886,"width":18,"height":10},"offset":{"x":0,"y":0},"originalSize":{"width":18,"height":10},"rotated":false,"capInsets":[0,0,0,0],"vertices":{"rawPosition":[],"indexes":[],"uv":[],"nuv":[],"minPos":{"x":0,"y":0,"z":0},"maxPos":{"x":0,"y":0,"z":0}},"packable":true,"pixelsToUnit":100,"pivot":{"x":0.5,"y":0.5},"meshType":0}],[0],0,[0],[0],[0]],[[{"name":"pic_maintask_doing_0","rect":{"x":723,"y":923,"width":66,"height":64},"offset":{"x":-1,"y":7},"originalSize":{"width":80,"height":80},"rotated":false,"capInsets":[0,0,0,0],"vertices":{"rawPosition":[],"indexes":[],"uv":[],"nuv":[],"minPos":{"x":0,"y":0,"z":0},"maxPos":{"x":0,"y":0,"z":0}},"packable":true,"pixelsToUnit":100,"pivot":{"x":0.5,"y":0.5},"meshType":0}],[0],0,[0],[0],[0]],[[{"name":"btn_hangup_go","rect":{"x":737,"y":604,"width":74,"height":82},"offset":{"x":-1,"y":0},"originalSize":{"width":76,"height":82},"rotated":false,"capInsets":[0,0,0,0],"vertices":{"rawPosition":[],"indexes":[],"uv":[],"nuv":[],"minPos":{"x":0,"y":0,"z":0},"maxPos":{"x":0,"y":0,"z":0}},"packable":true,"pixelsToUnit":100,"pivot":{"x":0.5,"y":0.5},"meshType":0}],[0],0,[0],[0],[0]],[[{"name":"pic_hangup_go_pkq_1","rect":{"x":308,"y":980,"width":70,"height":34},"offset":{"x":0,"y":0},"originalSize":{"width":70,"height":34},"rotated":false,"capInsets":[0,0,0,0],"vertices":{"rawPosition":[],"indexes":[],"uv":[],"nuv":[],"minPos":{"x":0,"y":0,"z":0},"maxPos":{"x":0,"y":0,"z":0}},"packable":true,"pixelsToUnit":100,"pivot":{"x":0.5,"y":0.5},"meshType":0}],[0],0,[0],[0],[0]],[[{"name":"box_hangup_chapter_02","rect":{"x":813,"y":610,"width":89,"height":100},"offset":{"x":-1,"y":0},"originalSize":{"width":91,"height":100},"rotated":false,"capInsets":[0,0,0,0],"vertices":{"rawPosition":[],"indexes":[],"uv":[],"nuv":[],"minPos":{"x":0,"y":0,"z":0},"maxPos":{"x":0,"y":0,"z":0}},"packable":true,"pixelsToUnit":100,"pivot":{"x":0.5,"y":0.5},"meshType":0}],[0],0,[0],[0],[0]],[[{"name":"pic_hangup_exp_bg","rect":{"x":2,"y":864,"width":626,"height":86},"offset":{"x":0,"y":0},"originalSize":{"width":626,"height":86},"rotated":false,"capInsets":[0,0,0,0],"vertices":{"rawPosition":[],"indexes":[],"uv":[],"nuv":[],"minPos":{"x":0,"y":0,"z":0},"maxPos":{"x":0,"y":0,"z":0}},"packable":true,"pixelsToUnit":100,"pivot":{"x":0.5,"y":0.5},"meshType":0}],[0],0,[0],[0],[0]],[[{"name":"pic_hangup_go_pkq_2","rect":{"x":552,"y":952,"width":75,"height":46},"offset":{"x":0,"y":0},"originalSize":{"width":75,"height":46},"rotated":false,"capInsets":[0,0,0,0],"vertices":{"rawPosition":[],"indexes":[],"uv":[],"nuv":[],"minPos":{"x":0,"y":0,"z":0},"maxPos":{"x":0,"y":0,"z":0}},"packable":true,"pixelsToUnit":100,"pivot":{"x":0.5,"y":0.5},"meshType":0}],[0],0,[0],[0],[0]],[[{"name":"pic_hangup_target_7","rect":{"x":831,"y":2,"width":134,"height":150},"offset":{"x":0,"y":0},"originalSize":{"width":134,"height":150},"rotated":false,"capInsets":[0,0,0,0],"vertices":{"rawPosition":[],"indexes":[],"uv":[],"nuv":[],"minPos":{"x":0,"y":0,"z":0},"maxPos":{"x":0,"y":0,"z":0}},"packable":true,"pixelsToUnit":100,"pivot":{"x":0.5,"y":0.5},"meshType":0}],[0],0,[0],[0],[0]],[[{"name":"pic_hangup_go_jng_2","rect":{"x":900,"y":732,"width":55,"height":52},"offset":{"x":4,"y":0},"originalSize":{"width":63,"height":52},"rotated":false,"capInsets":[0,0,0,0],"vertices":{"rawPosition":[],"indexes":[],"uv":[],"nuv":[],"minPos":{"x":0,"y":0,"z":0},"maxPos":{"x":0,"y":0,"z":0}},"packable":true,"pixelsToUnit":100,"pivot":{"x":0.5,"y":0.5},"meshType":0}],[0],0,[0],[0],[0]],[[{"name":"pic_hangup_search_coin","rect":{"x":2,"y":581,"width":343,"height":281},"offset":{"x":0,"y":0},"originalSize":{"width":343,"height":281},"rotated":false,"capInsets":[0,0,0,0],"vertices":{"rawPosition":[],"indexes":[],"uv":[],"nuv":[],"minPos":{"x":0,"y":0,"z":0},"maxPos":{"x":0,"y":0,"z":0}},"packable":true,"pixelsToUnit":100,"pivot":{"x":0.5,"y":0.5},"meshType":0}],[0],0,[0],[0],[0]],[[{"name":"pic_hangup_target_5","rect":{"x":680,"y":300,"width":134,"height":150},"offset":{"x":0,"y":0},"originalSize":{"width":134,"height":150},"rotated":false,"capInsets":[0,0,0,0],"vertices":{"rawPosition":[],"indexes":[],"uv":[],"nuv":[],"minPos":{"x":0,"y":0,"z":0},"maxPos":{"x":0,"y":0,"z":0}},"packable":true,"pixelsToUnit":100,"pivot":{"x":0.5,"y":0.5},"meshType":0}],[0],0,[0],[0],[0]],[[{"name":"pic_hangup_go_female","rect":{"x":904,"y":610,"width":56,"height":60},"offset":{"x":0,"y":0},"originalSize":{"width":56,"height":60},"rotated":false,"capInsets":[0,0,0,0],"vertices":{"rawPosition":[],"indexes":[],"uv":[],"nuv":[],"minPos":{"x":0,"y":0,"z":0},"maxPos":{"x":0,"y":0,"z":0}},"packable":true,"pixelsToUnit":100,"pivot":{"x":0.5,"y":0.5},"meshType":0}],[0],0,[0],[0],[0]],[[{"name":"aim_hangup_02","rect":{"x":886,"y":854,"width":52,"height":39},"offset":{"x":0,"y":0},"originalSize":{"width":52,"height":39},"rotated":false,"capInsets":[0,0,0,0],"vertices":{"rawPosition":[],"indexes":[],"uv":[],"nuv":[],"minPos":{"x":0,"y":0,"z":0},"maxPos":{"x":0,"y":0,"z":0}},"packable":true,"pixelsToUnit":100,"pivot":{"x":0.5,"y":0.5},"meshType":0}],[0],0,[0],[0],[0]],[[{"name":"pic_hangup_search_stone_2","rect":{"x":465,"y":300,"width":15,"height":18},"offset":{"x":0,"y":0},"originalSize":{"width":15,"height":18},"rotated":false,"capInsets":[0,0,0,0],"vertices":{"rawPosition":[],"indexes":[],"uv":[],"nuv":[],"minPos":{"x":0,"y":0,"z":0},"maxPos":{"x":0,"y":0,"z":0}},"packable":true,"pixelsToUnit":100,"pivot":{"x":0.5,"y":0.5},"meshType":0}],[0],0,[0],[0],[0]],[[{"name":"box_hangup_chapter_01","rect":{"x":630,"y":858,"width":91,"height":100},"offset":{"x":0,"y":0},"originalSize":{"width":91,"height":100},"rotated":false,"capInsets":[0,0,0,0],"vertices":{"rawPosition":[],"indexes":[],"uv":[],"nuv":[],"minPos":{"x":0,"y":0,"z":0},"maxPos":{"x":0,"y":0,"z":0}},"packable":true,"pixelsToUnit":100,"pivot":{"x":0.5,"y":0.5},"meshType":0}],[0],0,[0],[0],[0]],[[{"name":"pic_hangup_go_xhl_2","rect":{"x":629,"y":960,"width":78,"height":51},"offset":{"x":0,"y":10},"originalSize":{"width":78,"height":71},"rotated":false,"capInsets":[0,0,0,0],"vertices":{"rawPosition":[],"indexes":[],"uv":[],"nuv":[],"minPos":{"x":0,"y":0,"z":0},"maxPos":{"x":0,"y":0,"z":0}},"packable":true,"pixelsToUnit":100,"pivot":{"x":0.5,"y":0.5},"meshType":0}],[0],0,[0],[0],[0]],[[{"name":"pic_hangup_target_6","rect":{"x":831,"y":154,"width":134,"height":150},"offset":{"x":0,"y":0},"originalSize":{"width":134,"height":150},"rotated":false,"capInsets":[0,0,0,0],"vertices":{"rawPosition":[],"indexes":[],"uv":[],"nuv":[],"minPos":{"x":0,"y":0,"z":0},"maxPos":{"x":0,"y":0,"z":0}},"packable":true,"pixelsToUnit":100,"pivot":{"x":0.5,"y":0.5},"meshType":0}],[0],0,[0],[0],[0]],[[{"name":"pic_hangup_go_jng_1","rect":{"x":897,"y":895,"width":41,"height":46},"offset":{"x":0,"y":0},"originalSize":{"width":41,"height":46},"rotated":false,"capInsets":[0,0,0,0],"vertices":{"rawPosition":[],"indexes":[],"uv":[],"nuv":[],"minPos":{"x":0,"y":0,"z":0},"maxPos":{"x":0,"y":0,"z":0}},"packable":true,"pixelsToUnit":100,"pivot":{"x":0.5,"y":0.5},"meshType":0}],[0],0,[0],[0],[0]],[[{"name":"pic_hangup_go_xhl","rect":{"x":192,"y":980,"width":38,"height":40},"offset":{"x":0,"y":0},"originalSize":{"width":38,"height":40},"rotated":false,"capInsets":[0,0,0,0],"vertices":{"rawPosition":[],"indexes":[],"uv":[],"nuv":[],"minPos":{"x":0,"y":0,"z":0},"maxPos":{"x":0,"y":0,"z":0}},"packable":true,"pixelsToUnit":100,"pivot":{"x":0.5,"y":0.5},"meshType":0}],[0],0,[0],[0],[0]],[[{"name":"pic_maintask_done_0","rect":{"x":896,"y":786,"width":66,"height":66},"offset":{"x":-1,"y":7},"originalSize":{"width":80,"height":80},"rotated":false,"capInsets":[0,0,0,0],"vertices":{"rawPosition":[],"indexes":[],"uv":[],"nuv":[],"minPos":{"x":0,"y":0,"z":0},"maxPos":{"x":0,"y":0,"z":0}},"packable":true,"pixelsToUnit":100,"pivot":{"x":0.5,"y":0.5},"meshType":0}],[0],0,[0],[0],[0]],[[{"name":"pic_hangup_search_exp","rect":{"x":410,"y":322,"width":268,"height":293},"offset":{"x":-1,"y":1},"originalSize":{"width":278,"height":295},"rotated":false,"capInsets":[0,0,0,0],"vertices":{"rawPosition":[],"indexes":[],"uv":[],"nuv":[],"minPos":{"x":0,"y":0,"z":0},"maxPos":{"x":0,"y":0,"z":0}},"packable":true,"pixelsToUnit":100,"pivot":{"x":0.5,"y":0.5},"meshType":0}],[0],0,[0],[0],[0]],[[{"name":"pic_hangup_search_coin_1","rect":{"x":347,"y":617,"width":252,"height":231},"offset":{"x":0,"y":0},"originalSize":{"width":252,"height":231},"rotated":false,"capInsets":[0,0,0,0],"vertices":{"rawPosition":[],"indexes":[],"uv":[],"nuv":[],"minPos":{"x":0,"y":0,"z":0},"maxPos":{"x":0,"y":0,"z":0}},"packable":true,"pixelsToUnit":100,"pivot":{"x":0.5,"y":0.5},"meshType":0}],[0],0,[0],[0],[0]],[[{"name":"pic_hangup_search_exp_1","rect":{"x":601,"y":769,"width":91,"height":87},"offset":{"x":1,"y":1},"originalSize":{"width":93,"height":93},"rotated":false,"capInsets":[0,0,0,0],"vertices":{"rawPosition":[],"indexes":[],"uv":[],"nuv":[],"minPos":{"x":0,"y":0,"z":0},"maxPos":{"x":0,"y":0,"z":0}},"packable":true,"pixelsToUnit":100,"pivot":{"x":0.5,"y":0.5},"meshType":0}],[0],0,[0],[0],[0]],[[{"name":"pic_hangup_search_stone_1","rect":{"x":897,"y":984,"width":33,"height":36},"offset":{"x":0,"y":0},"originalSize":{"width":33,"height":36},"rotated":false,"capInsets":[0,0,0,0],"vertices":{"rawPosition":[],"indexes":[],"uv":[],"nuv":[],"minPos":{"x":0,"y":0,"z":0},"maxPos":{"x":0,"y":0,"z":0}},"packable":true,"pixelsToUnit":100,"pivot":{"x":0.5,"y":0.5},"meshType":0}],[0],0,[0],[0],[0]],[[{"name":"pic_hangup_buff_02","rect":{"x":232,"y":980,"width":74,"height":36},"offset":{"x":0,"y":0},"originalSize":{"width":74,"height":36},"rotated":false,"capInsets":[0,0,0,0],"vertices":{"rawPosition":[],"indexes":[],"uv":[],"nuv":[],"minPos":{"x":0,"y":0,"z":0},"maxPos":{"x":0,"y":0,"z":0}},"packable":true,"pixelsToUnit":100,"pivot":{"x":0.5,"y":0.5},"meshType":0}],[0],0,[0],[0],[0]],[[{"name":"pic_hangup_target_1_1","rect":{"x":830,"y":830,"width":54,"height":54},"offset":{"x":0,"y":0},"originalSize":{"width":54,"height":54},"rotated":false,"capInsets":[0,0,0,0],"vertices":{"rawPosition":[],"indexes":[],"uv":[],"nuv":[],"minPos":{"x":0,"y":0,"z":0},"maxPos":{"x":0,"y":0,"z":0}},"packable":true,"pixelsToUnit":100,"pivot":{"x":0.5,"y":0.5},"meshType":0}],[0],0,[0],[0],[0]],[[{"name":"pic_maintask_doing_1","rect":{"x":452,"y":980,"width":70,"height":22},"offset":{"x":-3,"y":-26},"originalSize":{"width":80,"height":80},"rotated":false,"capInsets":[0,0,0,0],"vertices":{"rawPosition":[],"indexes":[],"uv":[],"nuv":[],"minPos":{"x":0,"y":0,"z":0},"maxPos":{"x":0,"y":0,"z":0}},"packable":true,"pixelsToUnit":100,"pivot":{"x":0.5,"y":0.5},"meshType":0}],[0],0,[0],[0],[0]],[[{"name":"aim_hangup_01","rect":{"x":723,"y":849,"width":63,"height":72},"offset":{"x":0,"y":0},"originalSize":{"width":63,"height":72},"rotated":false,"capInsets":[0,0,0,0],"vertices":{"rawPosition":[],"indexes":[],"uv":[],"nuv":[],"minPos":{"x":0,"y":0,"z":0},"maxPos":{"x":0,"y":0,"z":0}},"packable":true,"pixelsToUnit":100,"pivot":{"x":0.5,"y":0.5},"meshType":0}],[0],0,[0],[0],[0]],[[{"name":"pic_maintask_done_1","rect":{"x":380,"y":980,"width":70,"height":22},"offset":{"x":-2,"y":-26},"originalSize":{"width":80,"height":80},"rotated":false,"capInsets":[0,0,0,0],"vertices":{"rawPosition":[],"indexes":[],"uv":[],"nuv":[],"minPos":{"x":0,"y":0,"z":0},"maxPos":{"x":0,"y":0,"z":0}},"packable":true,"pixelsToUnit":100,"pivot":{"x":0.5,"y":0.5},"meshType":0}],[0],0,[0],[0],[0]],[[{"name":"box_hangup_chapter_00","rect":{"x":809,"y":712,"width":89,"height":70},"offset":{"x":1,"y":-15},"originalSize":{"width":91,"height":100},"rotated":false,"capInsets":[0,0,0,0],"vertices":{"rawPosition":[],"indexes":[],"uv":[],"nuv":[],"minPos":{"x":0,"y":0,"z":0},"maxPos":{"x":0,"y":0,"z":0}},"packable":true,"pixelsToUnit":100,"pivot":{"x":0.5,"y":0.5},"meshType":0}],[0],0,[0],[0],[0]],[[{"name":"pic_hangup_target_3","rect":{"x":816,"y":306,"width":134,"height":150},"offset":{"x":0,"y":0},"originalSize":{"width":134,"height":150},"rotated":false,"capInsets":[0,0,0,0],"vertices":{"rawPosition":[],"indexes":[],"uv":[],"nuv":[],"minPos":{"x":0,"y":0,"z":0},"maxPos":{"x":0,"y":0,"z":0}},"packable":true,"pixelsToUnit":100,"pivot":{"x":0.5,"y":0.5},"meshType":0}],[0],0,[0],[0],[0]],[[{"name":"aim_hangup_03","rect":{"x":791,"y":969,"width":52,"height":41},"offset":{"x":0,"y":0},"originalSize":{"width":52,"height":41},"rotated":false,"capInsets":[0,0,0,0],"vertices":{"rawPosition":[],"indexes":[],"uv":[],"nuv":[],"minPos":{"x":0,"y":0,"z":0},"maxPos":{"x":0,"y":0,"z":0}},"packable":true,"pixelsToUnit":100,"pivot":{"x":0.5,"y":0.5},"meshType":0}],[0],0,[0],[0],[0]],[[{"name":"exp_hangup_01","rect":{"x":465,"y":280,"width":350,"height":18},"offset":{"x":0,"y":0},"originalSize":{"width":358,"height":26},"rotated":false,"capInsets":[0,0,0,0],"vertices":{"rawPosition":[],"indexes":[],"uv":[],"nuv":[],"minPos":{"x":0,"y":0,"z":0},"maxPos":{"x":0,"y":0,"z":0}},"packable":true,"pixelsToUnit":100,"pivot":{"x":0.5,"y":0.5},"meshType":0}],[0],0,[0],[0],[0]]]]
