[1,["83IiGHcTxJS72mvSn7/Z+H@6c48a"],["_textureSource"],["cc.SpriteFrame","cc.SpriteAtlas"],0,[[[{"name":"ui_new_handbook_00","spriteFrames":["ui_new_handbook_01","e2BymmTM9Hm670oNGnYXlE@4d3d3","ui_new_handbook_02","e2BymmTM9Hm670oNGnYXlE@bab11","ui_new_handbook_03","e2BymmTM9Hm670oNGnYXlE@8e2f5","ui_new_handbook_04","e2BymmTM9Hm670oNGnYXlE@a6e63","ui_new_handbook_05","e2BymmTM9Hm670oNGnYXlE@a5b02","ui_new_handbook_06","e2BymmTM9Hm670oNGnYXlE@3f66d","ui_new_handbook_07","e2BymmTM9Hm670oNGnYXlE@74d53","ui_new_handbook_08","e2BymmTM9Hm670oNGnYXlE@1522b","ui_new_handbook__bg_01","e2BymmTM9Hm670oNGnYXlE@021d8","ui_new_handbook__bg_02","e2BymmTM9Hm670oNGnYXlE@71e39","ui_new_handbook__bg_03","e2BymmTM9Hm670oNGnYXlE@287f0","ui_new_handbook__bg_04","e2BymmTM9Hm670oNGnYXlE@a04e3","ui_new_handbook__bg_05","e2BymmTM9Hm670oNGnYXlE@a7769","ui_new_handbook__bg_06","e2BymmTM9Hm670oNGnYXlE@d8907","ui_new_handbook__bg_07","e2BymmTM9Hm670oNGnYXlE@70b11","ui_new_handbook__bg_08","e2BymmTM9Hm670oNGnYXlE@1676b","ui_new_handbook__bg_09","e2BymmTM9Hm670oNGnYXlE@45969","ui_new_handbook__bg_10","e2BymmTM9Hm670oNGnYXlE@b1e70","ui_new_handbook__bg_11","e2BymmTM9Hm670oNGnYXlE@53f49","ui_new_handbook__bg_12","e2BymmTM9Hm670oNGnYXlE@7bccc","ui_new_handbook__bg_13","e2BymmTM9Hm670oNGnYXlE@f2047","ui_new_handbook__no1","e2BymmTM9Hm670oNGnYXlE@4d63f","ui_new_handbook__no2","e2BymmTM9Hm670oNGnYXlE@c0990","ui_new_handbook__no3","e2BymmTM9Hm670oNGnYXlE@89761","ui_new_handbook__txt_00","e2BymmTM9Hm670oNGnYXlE@8830a","ui_new_handbook__txt_01","e2BymmTM9Hm670oNGnYXlE@5932e","ui_new_handbook__txt_02","e2BymmTM9Hm670oNGnYXlE@b7ffe","ui_new_handbook__txt_03","e2BymmTM9Hm670oNGnYXlE@fe8f9","ui_new_handbook__txt_04","e2BymmTM9Hm670oNGnYXlE@6b63a","ui_new_handbook__txt_05","e2BymmTM9Hm670oNGnYXlE@80f9f","ui_new_handbook__txt_06","e2BymmTM9Hm670oNGnYXlE@96f60","ui_new_handbook_bt_00","e2BymmTM9Hm670oNGnYXlE@d6a10","ui_new_handbook_bt_01","e2BymmTM9Hm670oNGnYXlE@70108","ui_new_handbook_bt_02","e2BymmTM9Hm670oNGnYXlE@ee3cb","ui_new_handbook_bt_03","e2BymmTM9Hm670oNGnYXlE@5b01e","ui_new_handbook_bt_04","e2BymmTM9Hm670oNGnYXlE@c9701","ui_new_handbook_bt_05","e2BymmTM9Hm670oNGnYXlE@f9f8a","ui_new_handbook_bt_06","e2BymmTM9Hm670oNGnYXlE@4646c","ui_new_handbook_bt_07","e2BymmTM9Hm670oNGnYXlE@0ed7b","ui_new_handbook_bt_08","e2BymmTM9Hm670oNGnYXlE@cadbb","ui_new_handbook_bt_09","e2BymmTM9Hm670oNGnYXlE@a0eff","ui_new_handbook_bt_10","e2BymmTM9Hm670oNGnYXlE@59a0a","ui_new_handbook_bt_11","e2BymmTM9Hm670oNGnYXlE@c5853","ui_new_handbook_bt_12","e2BymmTM9Hm670oNGnYXlE@443ee","ui_new_handbook_bt_13","e2BymmTM9Hm670oNGnYXlE@d5805","ui_new_handbook_bt_14","e2BymmTM9Hm670oNGnYXlE@1feca","ui_new_handbook_bt_15","e2BymmTM9Hm670oNGnYXlE@be790","ui_new_handbook_bt_16","e2BymmTM9Hm670oNGnYXlE@ffb71","ui_new_handbook_bt_17","e2BymmTM9Hm670oNGnYXlE@d8fc8","ui_new_handbook_bt_18","e2BymmTM9Hm670oNGnYXlE@14b72","ui_new_handbook_bt_19","e2BymmTM9Hm670oNGnYXlE@c9108","ui_new_handbook_bt_20","e2BymmTM9Hm670oNGnYXlE@2f60b","ui_new_handbook_bt_21","e2BymmTM9Hm670oNGnYXlE@eeb98","ui_new_handbook_bt_22","e2BymmTM9Hm670oNGnYXlE@59fa4","ui_new_handbook_bt_23","e2BymmTM9Hm670oNGnYXlE@5d377","ui_new_handbook_bt_24","e2BymmTM9Hm670oNGnYXlE@b3c83","ui_new_handbook_bt_25","e2BymmTM9Hm670oNGnYXlE@8f557","ui_new_handbook_entrance","e2BymmTM9Hm670oNGnYXlE@84378","ui_new_handbook_ger_bg_1","e2BymmTM9Hm670oNGnYXlE@b9374","ui_new_handbook_ger_bg_2","e2BymmTM9Hm670oNGnYXlE@66770","ui_new_handbook_ger_bg_3","e2BymmTM9Hm670oNGnYXlE@a3bb2","ui_new_handbook_ger_bg_4","e2BymmTM9Hm670oNGnYXlE@559ca","ui_new_handbook_ger_bg_5","e2BymmTM9Hm670oNGnYXlE@4c655","ui_new_handbook_ger_bg_6","e2BymmTM9Hm670oNGnYXlE@617d8","ui_new_handbook_ger_bg_7","e2BymmTM9Hm670oNGnYXlE@0470a","ui_new_handbook_ger_bg_8","e2BymmTM9Hm670oNGnYXlE@e25f7","ui_new_handbook_ger_bg_9","e2BymmTM9Hm670oNGnYXlE@6b879","ui_new_handbook_icon","e2BymmTM9Hm670oNGnYXlE@5571c","ui_new_handbook_icon_0","e2BymmTM9Hm670oNGnYXlE@fb80e","ui_new_handbook_icon_1","e2BymmTM9Hm670oNGnYXlE@3a428","ui_new_handbook_icon_2","e2BymmTM9Hm670oNGnYXlE@a8c5d","ui_new_handbook_icon_3","e2BymmTM9Hm670oNGnYXlE@e0bd5","ui_new_handbook_icon_4","e2BymmTM9Hm670oNGnYXlE@5eb52","ui_new_handbook_icon_5","e2BymmTM9Hm670oNGnYXlE@3cac7","ui_new_handbook_icon_6","e2BymmTM9Hm670oNGnYXlE@a2f8e","ui_new_handbook_icon_7","e2BymmTM9Hm670oNGnYXlE@e5f21","ui_new_handbook_icon_8","e2BymmTM9Hm670oNGnYXlE@b7851","ui_new_handbook_icon_9","e2BymmTM9Hm670oNGnYXlE@1b819","ui_new_handbook_random","e2BymmTM9Hm670oNGnYXlE@8c4b7"]}],[1],0,[],[],[]],[[{"name":"ui_new_handbook__bg_01","rect":{"x":858,"y":879,"width":29,"height":29},"offset":{"x":0,"y":0},"originalSize":{"width":29,"height":29},"rotated":false,"capInsets":[9,9,9,9],"vertices":{"rawPosition":[],"indexes":[],"uv":[],"nuv":[],"minPos":{"x":0,"y":0,"z":0},"maxPos":{"x":0,"y":0,"z":0}},"packable":true,"pixelsToUnit":100,"pivot":{"x":0.5,"y":0.5},"meshType":0}],[0],0,[0],[0],[0]],[[{"name":"ui_new_handbook_ger_bg_7","rect":{"x":844,"y":360,"width":79,"height":81},"offset":{"x":0,"y":0},"originalSize":{"width":79,"height":81},"rotated":false,"capInsets":[0,0,0,0],"vertices":{"rawPosition":[],"indexes":[],"uv":[],"nuv":[],"minPos":{"x":0,"y":0,"z":0},"maxPos":{"x":0,"y":0,"z":0}},"packable":true,"pixelsToUnit":100,"pivot":{"x":0.5,"y":0.5},"meshType":0}],[0],0,[0],[0],[0]],[[{"name":"ui_new_handbook_bt_07","rect":{"x":806,"y":795,"width":67,"height":66},"offset":{"x":0,"y":0},"originalSize":{"width":67,"height":66},"rotated":false,"capInsets":[0,0,0,0],"vertices":{"rawPosition":[],"indexes":[],"uv":[],"nuv":[],"minPos":{"x":0,"y":0,"z":0},"maxPos":{"x":0,"y":0,"z":0}},"packable":true,"pixelsToUnit":100,"pivot":{"x":0.5,"y":0.5},"meshType":0}],[0],0,[0],[0],[0]],[[{"name":"ui_new_handbook_bt_18","rect":{"x":663,"y":764,"width":72,"height":79},"offset":{"x":0,"y":0},"originalSize":{"width":74,"height":79},"rotated":false,"capInsets":[0,0,0,0],"vertices":{"rawPosition":[],"indexes":[],"uv":[],"nuv":[],"minPos":{"x":0,"y":0,"z":0},"maxPos":{"x":0,"y":0,"z":0}},"packable":true,"pixelsToUnit":100,"pivot":{"x":0.5,"y":0.5},"meshType":0}],[0],0,[0],[0],[0]],[[{"name":"ui_new_handbook_08","rect":{"x":589,"y":457,"width":78,"height":82},"offset":{"x":-1,"y":1},"originalSize":{"width":96,"height":96},"rotated":false,"capInsets":[0,0,0,0],"vertices":{"rawPosition":[],"indexes":[],"uv":[],"nuv":[],"minPos":{"x":0,"y":0,"z":0},"maxPos":{"x":0,"y":0,"z":0}},"packable":true,"pixelsToUnit":100,"pivot":{"x":0.5,"y":0.5},"meshType":0}],[0],0,[0],[0],[0]],[[{"name":"ui_new_handbook__bg_08","rect":{"x":2,"y":2,"width":593,"height":367},"offset":{"x":0,"y":0},"originalSize":{"width":593,"height":367},"rotated":false,"capInsets":[0,0,0,0],"vertices":{"rawPosition":[],"indexes":[],"uv":[],"nuv":[],"minPos":{"x":0,"y":0,"z":0},"maxPos":{"x":0,"y":0,"z":0}},"packable":true,"pixelsToUnit":100,"pivot":{"x":0.5,"y":0.5},"meshType":0}],[0],0,[0],[0],[0]],[[{"name":"ui_new_handbook_icon_9","rect":{"x":648,"y":983,"width":14,"height":14},"offset":{"x":0,"y":0},"originalSize":{"width":14,"height":14},"rotated":false,"capInsets":[0,0,0,0],"vertices":{"rawPosition":[],"indexes":[],"uv":[],"nuv":[],"minPos":{"x":0,"y":0,"z":0},"maxPos":{"x":0,"y":0,"z":0}},"packable":true,"pixelsToUnit":100,"pivot":{"x":0.5,"y":0.5},"meshType":0}],[0],0,[0],[0],[0]],[[{"name":"ui_new_handbook_bt_14","rect":{"x":856,"y":70,"width":67,"height":66},"offset":{"x":0,"y":0},"originalSize":{"width":67,"height":66},"rotated":false,"capInsets":[0,0,0,0],"vertices":{"rawPosition":[],"indexes":[],"uv":[],"nuv":[],"minPos":{"x":0,"y":0,"z":0},"maxPos":{"x":0,"y":0,"z":0}},"packable":true,"pixelsToUnit":100,"pivot":{"x":0.5,"y":0.5},"meshType":0}],[0],0,[0],[0],[0]],[[{"name":"ui_new_handbook__bg_03","rect":{"x":875,"y":827,"width":47,"height":50},"offset":{"x":0,"y":0},"originalSize":{"width":47,"height":50},"rotated":false,"capInsets":[0,0,0,0],"vertices":{"rawPosition":[],"indexes":[],"uv":[],"nuv":[],"minPos":{"x":0,"y":0,"z":0},"maxPos":{"x":0,"y":0,"z":0}},"packable":true,"pixelsToUnit":100,"pivot":{"x":0.5,"y":0.5},"meshType":0}],[0],0,[0],[0],[0]],[[{"name":"ui_new_handbook_bt_20","rect":{"x":587,"y":674,"width":82,"height":66},"offset":{"x":0,"y":0},"originalSize":{"width":82,"height":66},"rotated":false,"capInsets":[0,0,0,0],"vertices":{"rawPosition":[],"indexes":[],"uv":[],"nuv":[],"minPos":{"x":0,"y":0,"z":0},"maxPos":{"x":0,"y":0,"z":0}},"packable":true,"pixelsToUnit":100,"pivot":{"x":0.5,"y":0.5},"meshType":0}],[0],0,[0],[0],[0]],[[{"name":"ui_new_handbook_icon_5","rect":{"x":720,"y":845,"width":14,"height":14},"offset":{"x":0,"y":0},"originalSize":{"width":14,"height":14},"rotated":false,"capInsets":[0,0,0,0],"vertices":{"rawPosition":[],"indexes":[],"uv":[],"nuv":[],"minPos":{"x":0,"y":0,"z":0},"maxPos":{"x":0,"y":0,"z":0}},"packable":true,"pixelsToUnit":100,"pivot":{"x":0.5,"y":0.5},"meshType":0}],[0],0,[0],[0],[0]],[[{"name":"ui_new_handbook_06","rect":{"x":589,"y":373,"width":82,"height":82},"offset":{"x":0,"y":-3},"originalSize":{"width":96,"height":96},"rotated":false,"capInsets":[0,0,0,0],"vertices":{"rawPosition":[],"indexes":[],"uv":[],"nuv":[],"minPos":{"x":0,"y":0,"z":0},"maxPos":{"x":0,"y":0,"z":0}},"packable":true,"pixelsToUnit":100,"pivot":{"x":0.5,"y":0.5},"meshType":0}],[0],0,[0],[0],[0]],[[{"name":"ui_new_handbook_bt_12","rect":{"x":856,"y":206,"width":67,"height":66},"offset":{"x":0,"y":0},"originalSize":{"width":67,"height":66},"rotated":false,"capInsets":[0,0,0,0],"vertices":{"rawPosition":[],"indexes":[],"uv":[],"nuv":[],"minPos":{"x":0,"y":0,"z":0},"maxPos":{"x":0,"y":0,"z":0}},"packable":true,"pixelsToUnit":100,"pivot":{"x":0.5,"y":0.5},"meshType":0}],[0],0,[0],[0],[0]],[[{"name":"ui_new_handbook__bg_09","rect":{"x":597,"y":2,"width":202,"height":221},"offset":{"x":0,"y":0},"originalSize":{"width":202,"height":221},"rotated":false,"capInsets":[0,0,0,0],"vertices":{"rawPosition":[],"indexes":[],"uv":[],"nuv":[],"minPos":{"x":0,"y":0,"z":0},"maxPos":{"x":0,"y":0,"z":0}},"packable":true,"pixelsToUnit":100,"pivot":{"x":0.5,"y":0.5},"meshType":0}],[0],0,[0],[0],[0]],[[{"name":"ui_new_handbook_bt_06","rect":{"x":651,"y":847,"width":67,"height":66},"offset":{"x":0,"y":0},"originalSize":{"width":67,"height":66},"rotated":false,"capInsets":[0,0,0,0],"vertices":{"rawPosition":[],"indexes":[],"uv":[],"nuv":[],"minPos":{"x":0,"y":0,"z":0},"maxPos":{"x":0,"y":0,"z":0}},"packable":true,"pixelsToUnit":100,"pivot":{"x":0.5,"y":0.5},"meshType":0}],[0],0,[0],[0],[0]],[[{"name":"ui_new_handbook_ger_bg_5","rect":{"x":754,"y":374,"width":79,"height":81},"offset":{"x":0,"y":0},"originalSize":{"width":79,"height":81},"rotated":false,"capInsets":[0,0,0,0],"vertices":{"rawPosition":[],"indexes":[],"uv":[],"nuv":[],"minPos":{"x":0,"y":0,"z":0},"maxPos":{"x":0,"y":0,"z":0}},"packable":true,"pixelsToUnit":100,"pivot":{"x":0.5,"y":0.5},"meshType":0}],[0],0,[0],[0],[0]],[[{"name":"ui_new_handbook_01","rect":{"x":851,"y":274,"width":72,"height":84},"offset":{"x":-2,"y":-2},"originalSize":{"width":96,"height":96},"rotated":false,"capInsets":[0,0,0,0],"vertices":{"rawPosition":[],"indexes":[],"uv":[],"nuv":[],"minPos":{"x":0,"y":0,"z":0},"maxPos":{"x":0,"y":0,"z":0}},"packable":true,"pixelsToUnit":100,"pivot":{"x":0.5,"y":0.5},"meshType":0}],[0],0,[0],[0],[0]],[[{"name":"ui_new_handbook__no1","rect":{"x":677,"y":698,"width":56,"height":50},"offset":{"x":0,"y":0},"originalSize":{"width":56,"height":50},"rotated":false,"capInsets":[0,0,0,0],"vertices":{"rawPosition":[],"indexes":[],"uv":[],"nuv":[],"minPos":{"x":0,"y":0,"z":0},"maxPos":{"x":0,"y":0,"z":0}},"packable":true,"pixelsToUnit":100,"pivot":{"x":0.5,"y":0.5},"meshType":0}],[0],0,[0],[0],[0]],[[{"name":"ui_new_handbook__bg_11","rect":{"x":801,"y":2,"width":53,"height":221},"offset":{"x":0,"y":0},"originalSize":{"width":53,"height":221},"rotated":false,"capInsets":[0,0,0,0],"vertices":{"rawPosition":[],"indexes":[],"uv":[],"nuv":[],"minPos":{"x":0,"y":0,"z":0},"maxPos":{"x":0,"y":0,"z":0}},"packable":true,"pixelsToUnit":100,"pivot":{"x":0.5,"y":0.5},"meshType":0}],[0],0,[0],[0],[0]],[[{"name":"ui_new_handbook_ger_bg_4","rect":{"x":749,"y":457,"width":79,"height":81},"offset":{"x":0,"y":0},"originalSize":{"width":79,"height":81},"rotated":false,"capInsets":[0,0,0,0],"vertices":{"rawPosition":[],"indexes":[],"uv":[],"nuv":[],"minPos":{"x":0,"y":0,"z":0},"maxPos":{"x":0,"y":0,"z":0}},"packable":true,"pixelsToUnit":100,"pivot":{"x":0.5,"y":0.5},"meshType":0}],[0],0,[0],[0],[0]],[[{"name":"ui_new_handbook__txt_01","rect":{"x":756,"y":540,"width":96,"height":26},"offset":{"x":0,"y":0},"originalSize":{"width":96,"height":26},"rotated":false,"capInsets":[0,0,0,0],"vertices":{"rawPosition":[],"indexes":[],"uv":[],"nuv":[],"minPos":{"x":0,"y":0,"z":0},"maxPos":{"x":0,"y":0,"z":0}},"packable":true,"pixelsToUnit":100,"pivot":{"x":0.5,"y":0.5},"meshType":0}],[0],0,[0],[0],[0]],[[{"name":"ui_new_handbook_bt_10","rect":{"x":737,"y":725,"width":67,"height":66},"offset":{"x":0,"y":0},"originalSize":{"width":67,"height":66},"rotated":false,"capInsets":[0,0,0,0],"vertices":{"rawPosition":[],"indexes":[],"uv":[],"nuv":[],"minPos":{"x":0,"y":0,"z":0},"maxPos":{"x":0,"y":0,"z":0}},"packable":true,"pixelsToUnit":100,"pivot":{"x":0.5,"y":0.5},"meshType":0}],[0],0,[0],[0],[0]],[[{"name":"ui_new_handbook_bt_22","rect":{"x":830,"y":457,"width":51,"height":54},"offset":{"x":0,"y":0},"originalSize":{"width":51,"height":54},"rotated":false,"capInsets":[0,0,0,0],"vertices":{"rawPosition":[],"indexes":[],"uv":[],"nuv":[],"minPos":{"x":0,"y":0,"z":0},"maxPos":{"x":0,"y":0,"z":0}},"packable":true,"pixelsToUnit":100,"pivot":{"x":0.5,"y":0.5},"meshType":0}],[0],0,[0],[0],[0]],[[{"name":"ui_new_handbook_bt_03","rect":{"x":717,"y":929,"width":67,"height":66},"offset":{"x":0,"y":0},"originalSize":{"width":67,"height":66},"rotated":false,"capInsets":[0,0,0,0],"vertices":{"rawPosition":[],"indexes":[],"uv":[],"nuv":[],"minPos":{"x":0,"y":0,"z":0},"maxPos":{"x":0,"y":0,"z":0}},"packable":true,"pixelsToUnit":100,"pivot":{"x":0.5,"y":0.5},"meshType":0}],[0],0,[0],[0],[0]],[[{"name":"ui_new_handbook_bt_23","rect":{"x":345,"y":905,"width":139,"height":63},"offset":{"x":0,"y":0},"originalSize":{"width":139,"height":63},"rotated":false,"capInsets":[0,0,0,0],"vertices":{"rawPosition":[],"indexes":[],"uv":[],"nuv":[],"minPos":{"x":0,"y":0,"z":0},"maxPos":{"x":0,"y":0,"z":0}},"packable":true,"pixelsToUnit":100,"pivot":{"x":0.5,"y":0.5},"meshType":0}],[0],0,[0],[0],[0]],[[{"name":"ui_new_handbook_icon_4","rect":{"x":858,"y":910,"width":12,"height":14},"offset":{"x":0,"y":0},"originalSize":{"width":14,"height":14},"rotated":false,"capInsets":[0,0,0,0],"vertices":{"rawPosition":[],"indexes":[],"uv":[],"nuv":[],"minPos":{"x":0,"y":0,"z":0},"maxPos":{"x":0,"y":0,"z":0}},"packable":true,"pixelsToUnit":100,"pivot":{"x":0.5,"y":0.5},"meshType":0}],[0],0,[0],[0],[0]],[[{"name":"ui_new_handbook_ger_bg_6","rect":{"x":673,"y":374,"width":79,"height":81},"offset":{"x":0,"y":0},"originalSize":{"width":79,"height":81},"rotated":false,"capInsets":[0,0,0,0],"vertices":{"rawPosition":[],"indexes":[],"uv":[],"nuv":[],"minPos":{"x":0,"y":0,"z":0},"maxPos":{"x":0,"y":0,"z":0}},"packable":true,"pixelsToUnit":100,"pivot":{"x":0.5,"y":0.5},"meshType":0}],[0],0,[0],[0],[0]],[[{"name":"ui_new_handbook__txt_04","rect":{"x":584,"y":742,"width":91,"height":20},"offset":{"x":0,"y":0},"originalSize":{"width":91,"height":20},"rotated":false,"capInsets":[0,0,0,0],"vertices":{"rawPosition":[],"indexes":[],"uv":[],"nuv":[],"minPos":{"x":0,"y":0,"z":0},"maxPos":{"x":0,"y":0,"z":0}},"packable":true,"pixelsToUnit":100,"pivot":{"x":0.5,"y":0.5},"meshType":0}],[0],0,[0],[0],[0]],[[{"name":"ui_new_handbook_ger_bg_9","rect":{"x":486,"y":916,"width":79,"height":81},"offset":{"x":0,"y":0},"originalSize":{"width":79,"height":81},"rotated":false,"capInsets":[0,0,0,0],"vertices":{"rawPosition":[],"indexes":[],"uv":[],"nuv":[],"minPos":{"x":0,"y":0,"z":0},"maxPos":{"x":0,"y":0,"z":0}},"packable":true,"pixelsToUnit":100,"pivot":{"x":0.5,"y":0.5},"meshType":0}],[0],0,[0],[0],[0]],[[{"name":"ui_new_handbook_bt_01","rect":{"x":786,"y":931,"width":67,"height":66},"offset":{"x":0,"y":0},"originalSize":{"width":67,"height":66},"rotated":false,"capInsets":[0,0,0,0],"vertices":{"rawPosition":[],"indexes":[],"uv":[],"nuv":[],"minPos":{"x":0,"y":0,"z":0},"maxPos":{"x":0,"y":0,"z":0}},"packable":true,"pixelsToUnit":100,"pivot":{"x":0.5,"y":0.5},"meshType":0}],[0],0,[0],[0],[0]],[[{"name":"ui_new_handbook__bg_07","rect":{"x":2,"y":735,"width":580,"height":21},"offset":{"x":0,"y":0},"originalSize":{"width":580,"height":21},"rotated":false,"capInsets":[0,0,0,0],"vertices":{"rawPosition":[],"indexes":[],"uv":[],"nuv":[],"minPos":{"x":0,"y":0,"z":0},"maxPos":{"x":0,"y":0,"z":0}},"packable":true,"pixelsToUnit":100,"pivot":{"x":0.5,"y":0.5},"meshType":0}],[0],0,[0],[0],[0]],[[{"name":"ui_new_handbook_07","rect":{"x":492,"y":758,"width":88,"height":80},"offset":{"x":-2,"y":1},"originalSize":{"width":96,"height":96},"rotated":false,"capInsets":[0,0,0,0],"vertices":{"rawPosition":[],"indexes":[],"uv":[],"nuv":[],"minPos":{"x":0,"y":0,"z":0},"maxPos":{"x":0,"y":0,"z":0}},"packable":true,"pixelsToUnit":100,"pivot":{"x":0.5,"y":0.5},"meshType":0}],[0],0,[0],[0],[0]],[[{"name":"ui_new_handbook__bg_12","rect":{"x":883,"y":443,"width":31,"height":31},"offset":{"x":0,"y":0},"originalSize":{"width":31,"height":31},"rotated":false,"capInsets":[0,0,0,0],"vertices":{"rawPosition":[],"indexes":[],"uv":[],"nuv":[],"minPos":{"x":0,"y":0,"z":0},"maxPos":{"x":0,"y":0,"z":0}},"packable":true,"pixelsToUnit":100,"pivot":{"x":0.5,"y":0.5},"meshType":0}],[0],0,[0],[0],[0]],[[{"name":"ui_new_handbook__txt_05","rect":{"x":589,"y":541,"width":109,"height":20},"offset":{"x":0,"y":0},"originalSize":{"width":109,"height":20},"rotated":false,"capInsets":[0,0,0,0],"vertices":{"rawPosition":[],"indexes":[],"uv":[],"nuv":[],"minPos":{"x":0,"y":0,"z":0},"maxPos":{"x":0,"y":0,"z":0}},"packable":true,"pixelsToUnit":100,"pivot":{"x":0.5,"y":0.5},"meshType":0}],[0],0,[0],[0],[0]],[[{"name":"ui_new_handbook_entrance","rect":{"x":735,"y":649,"width":76,"height":74},"offset":{"x":-1,"y":-1},"originalSize":{"width":80,"height":80},"rotated":false,"capInsets":[0,0,0,0],"vertices":{"rawPosition":[],"indexes":[],"uv":[],"nuv":[],"minPos":{"x":0,"y":0,"z":0},"maxPos":{"x":0,"y":0,"z":0}},"packable":true,"pixelsToUnit":100,"pivot":{"x":0.5,"y":0.5},"meshType":0}],[0],0,[0],[0],[0]],[[{"name":"ui_new_handbook__txt_00","rect":{"x":345,"y":970,"width":122,"height":27},"offset":{"x":0,"y":0},"originalSize":{"width":122,"height":27},"rotated":false,"capInsets":[0,0,0,0],"vertices":{"rawPosition":[],"indexes":[],"uv":[],"nuv":[],"minPos":{"x":0,"y":0,"z":0},"maxPos":{"x":0,"y":0,"z":0}},"packable":true,"pixelsToUnit":100,"pivot":{"x":0.5,"y":0.5},"meshType":0}],[0],0,[0],[0],[0]],[[{"name":"ui_new_handbook__no3","rect":{"x":875,"y":727,"width":48,"height":46},"offset":{"x":0,"y":-1},"originalSize":{"width":56,"height":50},"rotated":false,"capInsets":[0,0,0,0],"vertices":{"rawPosition":[],"indexes":[],"uv":[],"nuv":[],"minPos":{"x":0,"y":0,"z":0},"maxPos":{"x":0,"y":0,"z":0}},"packable":true,"pixelsToUnit":100,"pivot":{"x":0.5,"y":0.5},"meshType":0}],[0],0,[0],[0],[0]],[[{"name":"ui_new_handbook_random","rect":{"x":492,"y":840,"width":88,"height":74},"offset":{"x":1,"y":2},"originalSize":{"width":96,"height":96},"rotated":false,"capInsets":[0,0,0,0],"vertices":{"rawPosition":[],"indexes":[],"uv":[],"nuv":[],"minPos":{"x":0,"y":0,"z":0},"maxPos":{"x":0,"y":0,"z":0}},"packable":true,"pixelsToUnit":100,"pivot":{"x":0.5,"y":0.5},"meshType":0}],[0],0,[0],[0],[0]],[[{"name":"ui_new_handbook_03","rect":{"x":700,"y":290,"width":76,"height":82},"offset":{"x":1,"y":-1},"originalSize":{"width":96,"height":96},"rotated":false,"capInsets":[0,0,0,0],"vertices":{"rawPosition":[],"indexes":[],"uv":[],"nuv":[],"minPos":{"x":0,"y":0,"z":0},"maxPos":{"x":0,"y":0,"z":0}},"packable":true,"pixelsToUnit":100,"pivot":{"x":0.5,"y":0.5},"meshType":0}],[0],0,[0],[0],[0]],[[{"name":"ui_new_handbook_bt_25","rect":{"x":875,"y":775,"width":47,"height":50},"offset":{"x":0,"y":0},"originalSize":{"width":47,"height":50},"rotated":false,"capInsets":[0,0,0,0],"vertices":{"rawPosition":[],"indexes":[],"uv":[],"nuv":[],"minPos":{"x":0,"y":0,"z":0},"maxPos":{"x":0,"y":0,"z":0}},"packable":true,"pixelsToUnit":100,"pivot":{"x":0.5,"y":0.5},"meshType":0}],[0],0,[0],[0],[0]],[[{"name":"ui_new_handbook__txt_06","rect":{"x":579,"y":646,"width":96,"height":26},"offset":{"x":0,"y":0},"originalSize":{"width":96,"height":26},"rotated":false,"capInsets":[0,0,0,0],"vertices":{"rawPosition":[],"indexes":[],"uv":[],"nuv":[],"minPos":{"x":0,"y":0,"z":0},"maxPos":{"x":0,"y":0,"z":0}},"packable":true,"pixelsToUnit":100,"pivot":{"x":0.5,"y":0.5},"meshType":0}],[0],0,[0],[0],[0]],[[{"name":"ui_new_handbook__bg_04","rect":{"x":2,"y":684,"width":583,"height":49},"offset":{"x":0,"y":0},"originalSize":{"width":583,"height":49},"rotated":false,"capInsets":[0,0,0,0],"vertices":{"rawPosition":[],"indexes":[],"uv":[],"nuv":[],"minPos":{"x":0,"y":0,"z":0},"maxPos":{"x":0,"y":0,"z":0}},"packable":true,"pixelsToUnit":100,"pivot":{"x":0.5,"y":0.5},"meshType":0}],[0],0,[0],[0],[0]],[[{"name":"ui_new_handbook_bt_09","rect":{"x":806,"y":727,"width":67,"height":66},"offset":{"x":0,"y":0},"originalSize":{"width":67,"height":66},"rotated":false,"capInsets":[0,0,0,0],"vertices":{"rawPosition":[],"indexes":[],"uv":[],"nuv":[],"minPos":{"x":0,"y":0,"z":0},"maxPos":{"x":0,"y":0,"z":0}},"packable":true,"pixelsToUnit":100,"pivot":{"x":0.5,"y":0.5},"meshType":0}],[0],0,[0],[0],[0]],[[{"name":"ui_new_handbook_icon_6","rect":{"x":696,"y":983,"width":14,"height":14},"offset":{"x":0,"y":0},"originalSize":{"width":14,"height":14},"rotated":false,"capInsets":[0,0,0,0],"vertices":{"rawPosition":[],"indexes":[],"uv":[],"nuv":[],"minPos":{"x":0,"y":0,"z":0},"maxPos":{"x":0,"y":0,"z":0}},"packable":true,"pixelsToUnit":100,"pivot":{"x":0.5,"y":0.5},"meshType":0}],[0],0,[0],[0],[0]],[[{"name":"ui_new_handbook_ger_bg_3","rect":{"x":579,"y":563,"width":79,"height":81},"offset":{"x":0,"y":0},"originalSize":{"width":79,"height":81},"rotated":false,"capInsets":[0,0,0,0],"vertices":{"rawPosition":[],"indexes":[],"uv":[],"nuv":[],"minPos":{"x":0,"y":0,"z":0},"maxPos":{"x":0,"y":0,"z":0}},"packable":true,"pixelsToUnit":100,"pivot":{"x":0.5,"y":0.5},"meshType":0}],[0],0,[0],[0],[0]],[[{"name":"ui_new_handbook_05","rect":{"x":778,"y":286,"width":64,"height":86},"offset":{"x":2,"y":-2},"originalSize":{"width":96,"height":96},"rotated":false,"capInsets":[0,0,0,0],"vertices":{"rawPosition":[],"indexes":[],"uv":[],"nuv":[],"minPos":{"x":0,"y":0,"z":0},"maxPos":{"x":0,"y":0,"z":0}},"packable":true,"pixelsToUnit":100,"pivot":{"x":0.5,"y":0.5},"meshType":0}],[0],0,[0],[0],[0]],[[{"name":"ui_new_handbook_04","rect":{"x":813,"y":649,"width":70,"height":76},"offset":{"x":1,"y":-3},"originalSize":{"width":96,"height":96},"rotated":false,"capInsets":[0,0,0,0],"vertices":{"rawPosition":[],"indexes":[],"uv":[],"nuv":[],"minPos":{"x":0,"y":0,"z":0},"maxPos":{"x":0,"y":0,"z":0}},"packable":true,"pixelsToUnit":100,"pivot":{"x":0.5,"y":0.5},"meshType":0}],[0],0,[0],[0],[0]],[[{"name":"ui_new_handbook__bg_05","rect":{"x":345,"y":758,"width":145,"height":145},"offset":{"x":0,"y":0},"originalSize":{"width":145,"height":145},"rotated":false,"capInsets":[0,0,0,0],"vertices":{"rawPosition":[],"indexes":[],"uv":[],"nuv":[],"minPos":{"x":0,"y":0,"z":0},"maxPos":{"x":0,"y":0,"z":0}},"packable":true,"pixelsToUnit":100,"pivot":{"x":0.5,"y":0.5},"meshType":0}],[0],0,[0],[0],[0]],[[{"name":"ui_new_handbook_icon_2","rect":{"x":2,"y":981,"width":14,"height":14},"offset":{"x":0,"y":0},"originalSize":{"width":14,"height":14},"rotated":false,"capInsets":[0,0,0,0],"vertices":{"rawPosition":[],"indexes":[],"uv":[],"nuv":[],"minPos":{"x":0,"y":0,"z":0},"maxPos":{"x":0,"y":0,"z":0}},"packable":true,"pixelsToUnit":100,"pivot":{"x":0.5,"y":0.5},"meshType":0}],[0],0,[0],[0],[0]],[[{"name":"ui_new_handbook__bg_10","rect":{"x":2,"y":758,"width":341,"height":221},"offset":{"x":0,"y":0},"originalSize":{"width":341,"height":221},"rotated":false,"capInsets":[0,0,0,0],"vertices":{"rawPosition":[],"indexes":[],"uv":[],"nuv":[],"minPos":{"x":0,"y":0,"z":0},"maxPos":{"x":0,"y":0,"z":0}},"packable":true,"pixelsToUnit":100,"pivot":{"x":0.5,"y":0.5},"meshType":0}],[0],0,[0],[0],[0]],[[{"name":"ui_new_handbook_bt_24","rect":{"x":597,"y":225,"width":139,"height":63},"offset":{"x":0,"y":0},"originalSize":{"width":139,"height":63},"rotated":false,"capInsets":[0,0,0,0],"vertices":{"rawPosition":[],"indexes":[],"uv":[],"nuv":[],"minPos":{"x":0,"y":0,"z":0},"maxPos":{"x":0,"y":0,"z":0}},"packable":true,"pixelsToUnit":100,"pivot":{"x":0.5,"y":0.5},"meshType":0}],[0],0,[0],[0],[0]],[[{"name":"ui_new_handbook_icon_8","rect":{"x":664,"y":983,"width":14,"height":14},"offset":{"x":0,"y":0},"originalSize":{"width":14,"height":14},"rotated":false,"capInsets":[0,0,0,0],"vertices":{"rawPosition":[],"indexes":[],"uv":[],"nuv":[],"minPos":{"x":0,"y":0,"z":0},"maxPos":{"x":0,"y":0,"z":0}},"packable":true,"pixelsToUnit":100,"pivot":{"x":0.5,"y":0.5},"meshType":0}],[0],0,[0],[0],[0]],[[{"name":"ui_new_handbook__txt_02","rect":{"x":700,"y":541,"width":54,"height":20},"offset":{"x":0,"y":0},"originalSize":{"width":54,"height":20},"rotated":false,"capInsets":[0,0,0,0],"vertices":{"rawPosition":[],"indexes":[],"uv":[],"nuv":[],"minPos":{"x":0,"y":0,"z":0},"maxPos":{"x":0,"y":0,"z":0}},"packable":true,"pixelsToUnit":100,"pivot":{"x":0.5,"y":0.5},"meshType":0}],[0],0,[0],[0],[0]],[[{"name":"ui_new_handbook_ger_bg_1","rect":{"x":582,"y":764,"width":79,"height":81},"offset":{"x":0,"y":0},"originalSize":{"width":79,"height":81},"rotated":false,"capInsets":[0,0,0,0],"vertices":{"rawPosition":[],"indexes":[],"uv":[],"nuv":[],"minPos":{"x":0,"y":0,"z":0},"maxPos":{"x":0,"y":0,"z":0}},"packable":true,"pixelsToUnit":100,"pivot":{"x":0.5,"y":0.5},"meshType":0}],[0],0,[0],[0],[0]],[[{"name":"ui_new_handbook_02","rect":{"x":669,"y":457,"width":78,"height":82},"offset":{"x":-1,"y":0},"originalSize":{"width":96,"height":96},"rotated":false,"capInsets":[0,0,0,0],"vertices":{"rawPosition":[],"indexes":[],"uv":[],"nuv":[],"minPos":{"x":0,"y":0,"z":0},"maxPos":{"x":0,"y":0,"z":0}},"packable":true,"pixelsToUnit":100,"pivot":{"x":0.5,"y":0.5},"meshType":0}],[0],0,[0],[0],[0]],[[{"name":"ui_new_handbook_bt_15","rect":{"x":856,"y":2,"width":67,"height":66},"offset":{"x":0,"y":0},"originalSize":{"width":67,"height":66},"rotated":false,"capInsets":[0,0,0,0],"vertices":{"rawPosition":[],"indexes":[],"uv":[],"nuv":[],"minPos":{"x":0,"y":0,"z":0},"maxPos":{"x":0,"y":0,"z":0}},"packable":true,"pixelsToUnit":100,"pivot":{"x":0.5,"y":0.5},"meshType":0}],[0],0,[0],[0],[0]],[[{"name":"ui_new_handbook__no2","rect":{"x":677,"y":646,"width":56,"height":50},"offset":{"x":0,"y":0},"originalSize":{"width":56,"height":50},"rotated":false,"capInsets":[0,0,0,0],"vertices":{"rawPosition":[],"indexes":[],"uv":[],"nuv":[],"minPos":{"x":0,"y":0,"z":0},"maxPos":{"x":0,"y":0,"z":0}},"packable":true,"pixelsToUnit":100,"pivot":{"x":0.5,"y":0.5},"meshType":0}],[0],0,[0],[0],[0]],[[{"name":"ui_new_handbook_bt_11","rect":{"x":582,"y":847,"width":67,"height":66},"offset":{"x":0,"y":0},"originalSize":{"width":67,"height":66},"rotated":false,"capInsets":[0,0,0,0],"vertices":{"rawPosition":[],"indexes":[],"uv":[],"nuv":[],"minPos":{"x":0,"y":0,"z":0},"maxPos":{"x":0,"y":0,"z":0}},"packable":true,"pixelsToUnit":100,"pivot":{"x":0.5,"y":0.5},"meshType":0}],[0],0,[0],[0],[0]],[[{"name":"ui_new_handbook_bt_19","rect":{"x":738,"y":225,"width":111,"height":59},"offset":{"x":0,"y":0},"originalSize":{"width":111,"height":59},"rotated":false,"capInsets":[0,0,0,0],"vertices":{"rawPosition":[],"indexes":[],"uv":[],"nuv":[],"minPos":{"x":0,"y":0,"z":0},"maxPos":{"x":0,"y":0,"z":0}},"packable":true,"pixelsToUnit":100,"pivot":{"x":0.5,"y":0.5},"meshType":0}],[0],0,[0],[0],[0]],[[{"name":"ui_new_handbook_bt_04","rect":{"x":720,"y":861,"width":67,"height":66},"offset":{"x":0,"y":0},"originalSize":{"width":67,"height":66},"rotated":false,"capInsets":[0,0,0,0],"vertices":{"rawPosition":[],"indexes":[],"uv":[],"nuv":[],"minPos":{"x":0,"y":0,"z":0},"maxPos":{"x":0,"y":0,"z":0}},"packable":true,"pixelsToUnit":100,"pivot":{"x":0.5,"y":0.5},"meshType":0}],[0],0,[0],[0],[0]],[[{"name":"ui_new_handbook_bt_08","rect":{"x":737,"y":793,"width":67,"height":66},"offset":{"x":0,"y":0},"originalSize":{"width":67,"height":66},"rotated":false,"capInsets":[0,0,0,0],"vertices":{"rawPosition":[],"indexes":[],"uv":[],"nuv":[],"minPos":{"x":0,"y":0,"z":0},"maxPos":{"x":0,"y":0,"z":0}},"packable":true,"pixelsToUnit":100,"pivot":{"x":0.5,"y":0.5},"meshType":0}],[0],0,[0],[0],[0]],[[{"name":"ui_new_handbook_bt_13","rect":{"x":856,"y":138,"width":67,"height":66},"offset":{"x":0,"y":0},"originalSize":{"width":67,"height":66},"rotated":false,"capInsets":[0,0,0,0],"vertices":{"rawPosition":[],"indexes":[],"uv":[],"nuv":[],"minPos":{"x":0,"y":0,"z":0},"maxPos":{"x":0,"y":0,"z":0}},"packable":true,"pixelsToUnit":100,"pivot":{"x":0.5,"y":0.5},"meshType":0}],[0],0,[0],[0],[0]],[[{"name":"ui_new_handbook_bt_00","rect":{"x":855,"y":931,"width":67,"height":66},"offset":{"x":0,"y":0},"originalSize":{"width":67,"height":66},"rotated":false,"capInsets":[0,0,0,0],"vertices":{"rawPosition":[],"indexes":[],"uv":[],"nuv":[],"minPos":{"x":0,"y":0,"z":0},"maxPos":{"x":0,"y":0,"z":0}},"packable":true,"pixelsToUnit":100,"pivot":{"x":0.5,"y":0.5},"meshType":0}],[0],0,[0],[0],[0]],[[{"name":"ui_new_handbook__bg_06","rect":{"x":2,"y":371,"width":585,"height":169},"offset":{"x":0,"y":0},"originalSize":{"width":585,"height":169},"rotated":false,"capInsets":[0,0,0,0],"vertices":{"rawPosition":[],"indexes":[],"uv":[],"nuv":[],"minPos":{"x":0,"y":0,"z":0},"maxPos":{"x":0,"y":0,"z":0}},"packable":true,"pixelsToUnit":100,"pivot":{"x":0.5,"y":0.5},"meshType":0}],[0],0,[0],[0],[0]],[[{"name":"ui_new_handbook_bt_17","rect":{"x":741,"y":568,"width":74,"height":79},"offset":{"x":0,"y":0},"originalSize":{"width":74,"height":79},"rotated":false,"capInsets":[0,0,0,0],"vertices":{"rawPosition":[],"indexes":[],"uv":[],"nuv":[],"minPos":{"x":0,"y":0,"z":0},"maxPos":{"x":0,"y":0,"z":0}},"packable":true,"pixelsToUnit":100,"pivot":{"x":0.5,"y":0.5},"meshType":0}],[0],0,[0],[0],[0]],[[{"name":"ui_new_handbook_icon_3","rect":{"x":858,"y":863,"width":14,"height":14},"offset":{"x":0,"y":0},"originalSize":{"width":14,"height":14},"rotated":false,"capInsets":[0,0,0,0],"vertices":{"rawPosition":[],"indexes":[],"uv":[],"nuv":[],"minPos":{"x":0,"y":0,"z":0},"maxPos":{"x":0,"y":0,"z":0}},"packable":true,"pixelsToUnit":100,"pivot":{"x":0.5,"y":0.5},"meshType":0}],[0],0,[0],[0],[0]],[[{"name":"ui_new_handbook_ger_bg_8","rect":{"x":567,"y":916,"width":79,"height":81},"offset":{"x":0,"y":0},"originalSize":{"width":79,"height":81},"rotated":false,"capInsets":[0,0,0,0],"vertices":{"rawPosition":[],"indexes":[],"uv":[],"nuv":[],"minPos":{"x":0,"y":0,"z":0},"maxPos":{"x":0,"y":0,"z":0}},"packable":true,"pixelsToUnit":100,"pivot":{"x":0.5,"y":0.5},"meshType":0}],[0],0,[0],[0],[0]],[[{"name":"ui_new_handbook_icon_7","rect":{"x":680,"y":983,"width":14,"height":14},"offset":{"x":0,"y":0},"originalSize":{"width":14,"height":14},"rotated":false,"capInsets":[0,0,0,0],"vertices":{"rawPosition":[],"indexes":[],"uv":[],"nuv":[],"minPos":{"x":0,"y":0,"z":0},"maxPos":{"x":0,"y":0,"z":0}},"packable":true,"pixelsToUnit":100,"pivot":{"x":0.5,"y":0.5},"meshType":0}],[0],0,[0],[0],[0]],[[{"name":"ui_new_handbook_bt_02","rect":{"x":789,"y":863,"width":67,"height":66},"offset":{"x":0,"y":0},"originalSize":{"width":67,"height":66},"rotated":false,"capInsets":[0,0,0,0],"vertices":{"rawPosition":[],"indexes":[],"uv":[],"nuv":[],"minPos":{"x":0,"y":0,"z":0},"maxPos":{"x":0,"y":0,"z":0}},"packable":true,"pixelsToUnit":100,"pivot":{"x":0.5,"y":0.5},"meshType":0}],[0],0,[0],[0],[0]],[[{"name":"ui_new_handbook_bt_21","rect":{"x":597,"y":290,"width":101,"height":81},"offset":{"x":0,"y":0},"originalSize":{"width":101,"height":81},"rotated":false,"capInsets":[0,0,0,0],"vertices":{"rawPosition":[],"indexes":[],"uv":[],"nuv":[],"minPos":{"x":0,"y":0,"z":0},"maxPos":{"x":0,"y":0,"z":0}},"packable":true,"pixelsToUnit":100,"pivot":{"x":0.5,"y":0.5},"meshType":0}],[0],0,[0],[0],[0]],[[{"name":"ui_new_handbook__bg_13","rect":{"x":2,"y":542,"width":575,"height":140},"offset":{"x":0,"y":0},"originalSize":{"width":575,"height":140},"rotated":false,"capInsets":[0,0,0,0],"vertices":{"rawPosition":[],"indexes":[],"uv":[],"nuv":[],"minPos":{"x":0,"y":0,"z":0},"maxPos":{"x":0,"y":0,"z":0}},"packable":true,"pixelsToUnit":100,"pivot":{"x":0.5,"y":0.5},"meshType":0}],[0],0,[0],[0],[0]],[[{"name":"ui_new_handbook_bt_05","rect":{"x":648,"y":915,"width":67,"height":66},"offset":{"x":0,"y":0},"originalSize":{"width":67,"height":66},"rotated":false,"capInsets":[0,0,0,0],"vertices":{"rawPosition":[],"indexes":[],"uv":[],"nuv":[],"minPos":{"x":0,"y":0,"z":0},"maxPos":{"x":0,"y":0,"z":0}},"packable":true,"pixelsToUnit":100,"pivot":{"x":0.5,"y":0.5},"meshType":0}],[0],0,[0],[0],[0]],[[{"name":"ui_new_handbook_icon_0","rect":{"x":469,"y":970,"width":14,"height":14},"offset":{"x":0,"y":0},"originalSize":{"width":14,"height":14},"rotated":false,"capInsets":[0,0,0,0],"vertices":{"rawPosition":[],"indexes":[],"uv":[],"nuv":[],"minPos":{"x":0,"y":0,"z":0},"maxPos":{"x":0,"y":0,"z":0}},"packable":true,"pixelsToUnit":100,"pivot":{"x":0.5,"y":0.5},"meshType":0}],[0],0,[0],[0],[0]],[[{"name":"ui_new_handbook__txt_03","rect":{"x":867,"y":513,"width":37,"height":20},"offset":{"x":0,"y":0},"originalSize":{"width":37,"height":20},"rotated":false,"capInsets":[0,0,0,0],"vertices":{"rawPosition":[],"indexes":[],"uv":[],"nuv":[],"minPos":{"x":0,"y":0,"z":0},"maxPos":{"x":0,"y":0,"z":0}},"packable":true,"pixelsToUnit":100,"pivot":{"x":0.5,"y":0.5},"meshType":0}],[0],0,[0],[0],[0]],[[{"name":"ui_new_handbook_bt_16","rect":{"x":817,"y":568,"width":74,"height":79},"offset":{"x":0,"y":0},"originalSize":{"width":74,"height":79},"rotated":false,"capInsets":[0,0,0,0],"vertices":{"rawPosition":[],"indexes":[],"uv":[],"nuv":[],"minPos":{"x":0,"y":0,"z":0},"maxPos":{"x":0,"y":0,"z":0}},"packable":true,"pixelsToUnit":100,"pivot":{"x":0.5,"y":0.5},"meshType":0}],[0],0,[0],[0],[0]]]]
