[1,["a9bGElG7JA0L3ok+Gzm+6r@6c48a"],["_textureSource"],["cc.SpriteFrame"],0,[{"name":"car_ger_17292_bg.pvr","rect":{"x":3,"y":2,"width":72,"height":79},"offset":{"x":0.5,"y":0},"originalSize":{"width":77,"height":83},"rotated":false,"capInsets":[0,0,0,0],"vertices":{"rawPosition":[-36,-39.5,0,36,-39.5,0,-36,39.5,0,36,39.5,0],"indexes":[0,1,2,2,1,3],"uv":[3,81,75,81,3,2,75,2],"nuv":[0.03896103896103896,0.024096385542168676,0.974025974025974,0.024096385542168676,0.03896103896103896,0.9759036144578314,0.974025974025974,0.9759036144578314],"minPos":{"x":-36,"y":-39.5,"z":0},"maxPos":{"x":36,"y":39.5,"z":0}},"packable":true,"pixelsToUnit":100,"pivot":{"x":0.5,"y":0.5},"meshType":0}],[0],0,[0],[0],[0]]
