[1,["c4alxv4OBMZo5P8crkwJqH@6c48a"],["_textureSource"],["cc.SpriteFrame"],0,[{"name":"car_ger_15121_bg.pvr","rect":{"x":3,"y":3,"width":52,"height":68},"offset":{"x":0.5,"y":-0.5},"originalSize":{"width":57,"height":73},"rotated":false,"capInsets":[0,0,0,0],"vertices":{"rawPosition":[-26,-34,0,26,-34,0,-26,34,0,26,34,0],"indexes":[0,1,2,2,1,3],"uv":[3,70,55,70,3,2,55,2],"nuv":[0.05263157894736842,0.0273972602739726,0.9649122807017544,0.0273972602739726,0.05263157894736842,0.958904109589041,0.9649122807017544,0.958904109589041],"minPos":{"x":-26,"y":-34,"z":0},"maxPos":{"x":26,"y":34,"z":0}},"packable":true,"pixelsToUnit":100,"pivot":{"x":0.5,"y":0.5},"meshType":0}],[0],0,[0],[0],[0]]
